agp_api/__init__.py
agp_api/agent/__init__.py
agp_api/agent/agent_container.py
agp_api/gateway/__init__.py
agp_api/gateway/gateway_container.py
agp_api-0.0.6.dist-info/METADATA
agp_api-0.0.6.dist-info/WHEEL
agp_api-0.0.6.dist-info/RECORD
