Metadata-Version: 2.3
Name: agp-api
Version: 0.0.6
Summary: 
Author: brisacoder
Author-email: dev@brisa.ai
Requires-Python: >=3.12,<4.0
Classifier: Programming Language :: Python :: 3
Classifier: Programming Language :: Python :: 3.12
Classifier: Programming Language :: Python :: 3.13
Requires-Dist: agp-bindings (==0.1.14)
Requires-Dist: fastapi[standard] (==0.115.11)
Requires-Dist: pydantic (==2.10.6)
Requires-Dist: python-dotenv (==1.0.1)
Requires-Dist: sphinx (>=7.0,<8.0)
Requires-Dist: sphinx-rtd-theme (>=1.2,<2.0)
